risicompare/form.py
risicompare/html_delegate.py
risicompare/risicompare.py
risicompare-1.1.3.dist-info/LICENSE
risicompare-1.1.3.dist-info/METADATA
risicompare-1.1.3.dist-info/WHEEL
risicompare-1.1.3.dist-info/entry_points.txt
risicompare-1.1.3.dist-info/top_level.txt
risicompare-1.1.3.dist-info/RECORD
