Metadata-Version: 2.1
Name: risicompare
Version: 1.1.3
Summary: A script to get a risitas without offtopic messages, messages sorted in right order...
Home-page: https://github.com/vichelisdelapaz/risicompare
Author: Vichelis
Author-email: vichelis@prefecturedelapaz.com
License: UNKNOWN
Project-URL: Bug Tracker, https://github.com/vichelisdelapaz/risicompare/issues
Platform: UNKNOWN
Classifier: Programming Language :: Python :: 3
Classifier: License :: OSI Approved :: GNU General Public License v3 (GPLv3)
Classifier: Operating System :: OS Independent
Classifier: Intended Audience :: Developers
Classifier: Intended Audience :: End Users/Desktop
Requires-Python: >=3.6
License-File: LICENSE
Requires-Dist: BeautifulSoup4
Requires-Dist: lxml
Requires-Dist: PySide6
